{"GlobalPropertiesHash":"iD8+5t4uL8fuQHZg3jdn5kEbQgDFIPbMewRipdGC8OE=","FingerprintPatternsHash":"gq3WsqcKBUGTSNle7RKKyXRIwh7M8ccEqOqYvIzoM04=","PropertyOverridesHash":"8ZRc1sGeVrPBx4lD717BgRaQekyh78QKV9SKsdt638U=","InputHashes":["7g\u002BVWLntYRk\u002BRLkahMiB5oBUKYftTXWr/5OUdAstioA=","O6DjTfkI/zp10mGpyiF/jNRPMCMLXh7vgVJZ46NXH6A=","7ZJVjTpqisi8QXh5NisSmdE\u002B9dPAEJbtdFn\u002BwcfQczo=","wcmyHy2fWVog1ybdDyJzIuLeYfT5b1CBbi\u002BogwctsnU="],"CachedAssets":{"7g\u002BVWLntYRk\u002BRLkahMiB5oBUKYftTXWr/5OUdAstioA=":{"Identity":"D:\\Study\\Course\\Asp.net\\HW\\HW_5\\HW_5\\wwwroot\\index.html","SourceId":"HW_5","SourceType":"Discovered","ContentRoot":"D:\\Study\\Course\\Asp.net\\HW\\HW_5\\HW_5\\wwwroot\\","BasePath":"_content/HW_5","RelativePath":"index#[.{fingerprint}]?.html","AssetKind":"All","AssetMode":"All","AssetRole":"Primary","AssetMergeBehavior":null,"AssetMergeSource":"","RelatedAsset":null,"AssetTraitName":null,"AssetTraitValue":null,"Fingerprint":"kcm2y5u7lz","Integrity":"pBOnjX0xnjBhv7tVql/RjXbxyD/SQQ1P5btP1uuATUs=","CopyToOutputDirectory":"Never","CopyToPublishDirectory":"PreserveNewest","OriginalItemSpec":"wwwroot\\index.html","FileLength":1222,"LastWriteTime":"2025-09-14T11:21:50.3665158+00:00"},"O6DjTfkI/zp10mGpyiF/jNRPMCMLXh7vgVJZ46NXH6A=":{"Identity":"D:\\Study\\Course\\Asp.net\\HW\\HW_5\\HW_5\\wwwroot\\uploads\\b7ba0e3e-9722-4da7-9435-f28df24cdc97.jpg","SourceId":"HW_5","SourceType":"Discovered","ContentRoot":"D:\\Study\\Course\\Asp.net\\HW\\HW_5\\HW_5\\wwwroot\\","BasePath":"_content/HW_5","RelativePath":"uploads/b7ba0e3e-9722-4da7-9435-f28df24cdc97#[.{fingerprint}]?.jpg","AssetKind":"All","AssetMode":"All","AssetRole":"Primary","AssetMergeBehavior":null,"AssetMergeSource":"","RelatedAsset":null,"AssetTraitName":null,"AssetTraitValue":null,"Fingerprint":"qadxz3090n","Integrity":"bg8LdTlqK/6uneKJkJ/m1NY7pnFzPoAGqpprwUme8eo=","CopyToOutputDirectory":"Never","CopyToPublishDirectory":"PreserveNewest","OriginalItemSpec":"wwwroot\\uploads\\b7ba0e3e-9722-4da7-9435-f28df24cdc97.jpg","FileLength":90797,"LastWriteTime":"2025-09-14T11:25:52.5876339+00:00"}},"CachedCopyCandidates":{}}